README.md
setup.py
slicefix/__init__.py
slicefix/slicefix.py
slicefix_jonathandannel.egg-info/PKG-INFO
slicefix_jonathandannel.egg-info/SOURCES.txt
slicefix_jonathandannel.egg-info/dependency_links.txt
slicefix_jonathandannel.egg-info/entry_points.txt
slicefix_jonathandannel.egg-info/requires.txt
slicefix_jonathandannel.egg-info/top_level.txt