Metadata-Version: 2.1
Name: slicefix-jonathandannel
Version: 2.7.10
Summary: A simple script for formatting Photoshop HTML generated from image slicing
Home-page: https://github.com/jonathandannel/slicefixx
Author: Jonathan Dannel
Author-email: usixjad@gmail.com
License: UNKNOWN
Platform: UNKNOWN
Classifier: Programming Language :: Python :: 3
Classifier: License :: OSI Approved :: MIT License
Classifier: Operating System :: OS Independent
Requires-Python: >=3.7
